{"_id":{"$oid":"69673cd6b094ef62d921ca32"},"donorId":{"$oid":"6964a13a6f607b4cc898fde3"},"requesterId":{"$oid":"695f2879861ed964dd1de8e9"},"patientId":{"$oid":"6966132a72e2807977afa534"},"bloodGroup":"O+","status":"accepted","createdAt":{"$date":"2026-01-14T06:51:02.188Z"},"updatedAt":{"$date":"2026-01-16T05:38:27.495Z"},"__v":0}
{"_id":{"$oid":"69673ead4ad680d6b3eb3abf"},"donorId":{"$oid":"6964a13a6f607b4cc898fde3"},"requesterId":{"$oid":"695f2efdfb53e2fffd452d83"},"patientId":{"$oid":"6966132a72e2807977afa534"},"bloodGroup":"O+","status":"booked","createdAt":{"$date":"2026-01-14T06:58:53.575Z"},"updatedAt":{"$date":"2026-01-16T05:28:54.218Z"},"__v":0,"bookingId":{"$oid":"6969cc964204b72297c199f7"}}
{"_id":{"$oid":"69674a9eb258046baf9ab94c"},"donorId":{"$oid":"6964a13a6f607b4cc898fde3"},"requesterId":{"$oid":"695f2879861ed964dd1de8e9"},"patientId":{"$oid":"6966132a72e2807977afa534"},"bloodGroup":"O+","status":"booked","createdAt":{"$date":"2026-01-14T07:49:50.499Z"},"updatedAt":{"$date":"2026-01-15T08:27:13.498Z"},"__v":0,"bookingId":{"$oid":"6968a4e1f1c12840112f4cb4"}}
{"_id":{"$oid":"696866b95a27246cd0464b78"},"donorId":{"$oid":"6964a13a6f607b4cc898fde3"},"requesterId":{"$oid":"695f2879861ed964dd1de8e9"},"patientId":{"$oid":"6966132a72e2807977afa534"},"bloodGroup":"O+","status":"booked","createdAt":{"$date":"2026-01-15T04:02:01.959Z"},"updatedAt":{"$date":"2026-01-15T06:46:08.935Z"},"__v":0,"bookingId":{"$oid":"69688d30e7438cf841f390aa"}}
{"_id":{"$oid":"6968698cbc4a6b8cf44052fe"},"donorId":{"$oid":"6964a13a6f607b4cc898fde3"},"requesterId":{"$oid":"695f2879861ed964dd1de8e9"},"patientId":{"$oid":"6966132a72e2807977afa534"},"bloodGroup":"O+","status":"booked","createdAt":{"$date":"2026-01-15T04:14:04.176Z"},"updatedAt":{"$date":"2026-01-15T05:41:29.679Z"},"__v":0}
{"_id":{"$oid":"6969d7363cec07473133a7b8"},"donorId":{"$oid":"6964a13a6f607b4cc898fde3"},"requesterId":{"$oid":"695f2879861ed964dd1de8e9"},"patientId":{"$oid":"6966132a72e2807977afa534"},"bloodGroup":"O+","status":"booked","createdAt":{"$date":"2026-01-16T06:14:14.089Z"},"updatedAt":{"$date":"2026-01-16T08:37:16.087Z"},"__v":0,"bookingId":{"$oid":"6969f8bc872e9763b2193457"}}
